blogspotapi/__init__.py
blogspotapi/blog_client.py
blogspotapi/blog_repository.py
blogspotapi-1.0.2.dist-info/METADATA
blogspotapi-1.0.2.dist-info/WHEEL
blogspotapi-1.0.2.dist-info/top_level.txt
blogspotapi-1.0.2.dist-info/RECORD
