Metadata-Version: 2.1
Name: blogspotapi
Version: 1.0.2
Summary: Python Blogspot API Wrapper
Home-page: https://github.com/diegoami/blogspotapi/
Author: Diego Amicabile
Author-email: diego.amicabile@gmail.com
License: BSD License
Keywords: blogspot api wrapper
Platform: UNKNOWN
Classifier: Environment :: Web Environment
Classifier: Intended Audience :: Developers
Classifier: License :: OSI Approved :: BSD License
Classifier: Operating System :: OS Independent
Classifier: Programming Language :: Python
Classifier: Programming Language :: Python :: 3
Classifier: Topic :: Internet :: WWW/HTTP
Classifier: Topic :: Internet :: WWW/HTTP :: Dynamic Content
Classifier: Topic :: Internet :: WWW/HTTP :: HTTP Servers
Requires-Dist: requests
Requires-Dist: amaraapi
